<?xml version="1.0"?>
<odoo>
<data>
    <record id="view_form_singleton_clocking" model="ir.ui.view">
      <field name="name">Add Singleton Clocking Wizard</field>
      <field name="model">hr.employee.singletonclocking</field>
      <field name="view_type">form</field>
      <field name="arch" type="xml">
        <form>
          <group>
            <field name="employee_id"/>
            <field name="source"/>
          </group>
          <group>
            <field name="clocking_to_add_or_delete" />
          </group>
          <footer>
            <button type="object"
              name="button_add_clocking"
              string="Add Clocking"
            />
            <button special="cancel"
              string="Cancel"
              class="btn-secondary" />
          </footer>
        </form>
      </field>
    </record>

    <act_window id="action_singleton_clocking"
      name="Singleton Clocking"
      src_model="hr.employee"
      res_model="hr.employee.singletonclocking"
      view_type="form"
      view_mode="form"
      target="new"
      />

    <menuitem
      parent="hr.menu_hr_root"
      id="menu_wizard_singleton_clocking"
      action="action_singleton_clocking"
    />
</data>
</odoo>
